eai_sparsify-1.3.0.dist-info/licenses/LICENSE
sparsify/__init__.py
sparsify/__main__.py
sparsify/config.py
sparsify/data.py
sparsify/fused_encoder.py
sparsify/muon.py
sparsify/sign_sgd.py
sparsify/sparse_coder.py
sparsify/trainer.py
sparsify/utils.py
sparsify/xformers.py
sparsify/sparsify/sparse_coder.py
eai_sparsify-1.3.0.dist-info/METADATA
eai_sparsify-1.3.0.dist-info/WHEEL
eai_sparsify-1.3.0.dist-info/entry_points.txt
eai_sparsify-1.3.0.dist-info/top_level.txt
eai_sparsify-1.3.0.dist-info/RECORD
