Metadata-Version: 2.4
Name: eai-sparsify
Version: 1.3.0
Summary: Sparsify transformers with SAEs and transcoders
License: MIT License
Keywords: interpretability,explainable-ai
Requires-Python: >=3.10
License-File: LICENSE
Requires-Dist: accelerate
Requires-Dist: datasets
Requires-Dist: einops
Requires-Dist: huggingface-hub
Requires-Dist: natsort
Requires-Dist: safetensors
Requires-Dist: schedulefree
Requires-Dist: simple-parsing
Requires-Dist: torch
Requires-Dist: transformers
Provides-Extra: dev
Requires-Dist: pre-commit; extra == "dev"
Dynamic: license-file
